{
  "indexes": [
    {
      "collectionGroup": "whatsapp_session_requests",
      "queryScope": "COLLECTION",
      "fields": [
        { "fieldPath": "status", "order": "ASCENDING" },
        { "fieldPath": "requestedAt", "order": "ASCENDING" }
      ]
    },
    {
      "collectionGroup": "shopping_list_items",
      "queryScope": "COLLECTION",
      "fields": [
        { "fieldPath": "userId", "order": "ASCENDING" },
        { "fieldPath": "listDate", "order": "ASCENDING" },
        { "fieldPath": "name", "order": "ASCENDING" }
      ]
    },
    {
      "collectionGroup": "quotations",
      "queryScope": "COLLECTION",
      "fields": [
        { "fieldPath": "supplierIds", "arrayConfig": "CONTAINS" },
        { "fieldPath": "status", "order": "ASCENDING" },
        { "fieldPath": "deadline", "order": "DESCENDING" }
      ]
    },
    {
      "collectionGroup": "shopping_list_items",
      "queryScope": "COLLECTION_GROUP",
      "fields": [
        { "fieldPath": "status", "order": "ASCENDING" },
        { "fieldPath": "listDate", "order": "ASCENDING" }
      ]
    },
    {
      "collectionGroup": "quotations",
      "queryScope": "COLLECTION",
      "fields": [
        { "fieldPath": "createdAt", "order": "DESCENDING" },
        { "fieldPath": "shoppingListDate", "order": "ASCENDING" }
      ]
    },
    {
      "collectionGroup": "supplies",
      "queryScope": "COLLECTION",
      "fields": [
        { "fieldPath": "userId", "order": "ASCENDING" },
        { "fieldPath": "name", "order": "ASCENDING" }
      ]
    },
    {
      "collectionGroup": "shoppingListItems",
      "queryScope": "COLLECTION",
      "fields": [
        { "fieldPath": "userId", "order": "ASCENDING" },
        { "fieldPath": "listDate", "order": "ASCENDING" },
        { "fieldPath": "name", "order": "ASCENDING" }
      ]
    },
    {
      "collectionGroup": "shopping_list_items",
      "queryScope": "COLLECTION",
      "fields": [
        { "fieldPath": "userId", "order": "ASCENDING" },
        { "fieldPath": "listDate", "order": "ASCENDING" }
      ]
    },
    {
      "collectionGroup": "quotations",
      "queryScope": "COLLECTION",
      "fields": [
        { "fieldPath": "status", "order": "ASCENDING" },
        { "fieldPath": "deadline", "order": "ASCENDING" }
      ]
    },
    {
      "collectionGroup": "shopping_list_items",
      "queryScope": "COLLECTION",
      "fields": [
        { "fieldPath": "listId", "order": "ASCENDING" },
        { "fieldPath": "status", "order": "ASCENDING" }
      ]
    },
    {
      "collectionGroup": "brand_proposals",
      "queryScope": "COLLECTION",
      "fields": [
        { "fieldPath": "quotationId", "order": "ASCENDING" },
        { "fieldPath": "status", "order": "ASCENDING" },
        { "fieldPath": "createdAt", "order": "DESCENDING" }
      ]
    },
    {
      "collectionGroup": "user_sessions",
      "queryScope": "COLLECTION",
      "fields": [
        { "fieldPath": "status", "order": "ASCENDING" },
        { "fieldPath": "updatedAt", "order": "DESCENDING" }
      ]
    },
    {
      "collectionGroup": "quotations",
      "queryScope": "COLLECTION",
      "fields": [
        { "fieldPath": "status", "order": "ASCENDING" },
        { "fieldPath": "shoppingListDate", "order": "ASCENDING" }
      ]
    },
    {
      "collectionGroup": "fornecedores",
      "queryScope": "COLLECTION",
      "fields": [
        { "fieldPath": "userId", "order": "ASCENDING" },
        { "fieldPath": "empresa", "order": "ASCENDING" }
      ]
    },
    {
      "collectionGroup": "quotations",
      "queryScope": "COLLECTION",
      "fields": [
        { "fieldPath": "shoppingListDate", "order": "DESCENDING" },
        { "fieldPath": "createdAt", "order": "DESCENDING" }
      ]
    },
    {
      "collectionGroup": "quotations",
      "queryScope": "COLLECTION",
      "fields": [
        { "fieldPath": "userId", "order": "ASCENDING" },
        { "fieldPath": "shoppingListDate", "order": "ASCENDING" }
      ]
    },
    {
      "collectionGroup": "shopping_list_items",
      "queryScope": "COLLECTION",
      "fields": [
        { "fieldPath": "listDate", "order": "ASCENDING" },
        { "fieldPath": "status", "order": "ASCENDING" }
      ]
    },
    {
      "collectionGroup": "supply_categories",
      "queryScope": "COLLECTION",
      "fields": [
        { "fieldPath": "userId", "order": "ASCENDING" },
        { "fieldPath": "name", "order": "ASCENDING" }
      ]
    },
    {
      "collectionGroup": "fornecedores",
      "queryScope": "COLLECTION",
      "fields": [
        { "fieldPath": "status", "order": "ASCENDING" },
        { "fieldPath": "empresa", "order": "ASCENDING" }
      ]
    },
    {
      "collectionGroup": "incoming_messages",
      "queryScope": "COLLECTION",
      "fields": [
        { "fieldPath": "userId", "order": "ASCENDING" },
        { "fieldPath": "receivedAt", "order": "DESCENDING" }
      ]
    },
    {
      "collectionGroup": "supplies",
      "queryScope": "COLLECTION",
      "fields": [
        { "fieldPath": "userId", "order": "ASCENDING" },
        { "fieldPath": "categoryId", "order": "ASCENDING" },
        { "fieldPath": "name", "order": "ASCENDING" }
      ]
    },
    {
      "collectionGroup": "fornecedores",
      "queryScope": "COLLECTION",
      "fields": [
        { "fieldPath": "userId", "order": "ASCENDING" },
        { "fieldPath": "status", "order": "ASCENDING" },
        { "fieldPath": "empresa", "order": "ASCENDING" }
      ]
    },
    {
      "collectionGroup": "whatsapp_queue",
      "queryScope": "COLLECTION",
      "fields": [
        { "fieldPath": "status", "order": "ASCENDING" },
        { "fieldPath": "createdAt", "order": "ASCENDING" }
      ]
    },
    {
      "collectionGroup": "whatsapp_queue",
      "queryScope": "COLLECTION",
      "fields": [
        { "fieldPath": "userId", "order": "ASCENDING" },
        { "fieldPath": "status", "order": "ASCENDING" },
        { "fieldPath": "createdAt", "order": "ASCENDING" }
      ]
    },
    {
      "collectionGroup": "incoming_messages",
      "queryScope": "COLLECTION",
      "fields": [
        { "fieldPath": "isOutgoing", "order": "ASCENDING" },
        { "fieldPath": "status", "order": "ASCENDING" },
        { "fieldPath": "userId", "order": "ASCENDING" },
        { "fieldPath": "updatedAt", "order": "ASCENDING" }
      ]
    },
    {
      "collectionGroup": "notifications",
      "queryScope": "COLLECTION",
      "fields": [
        { "fieldPath": "userId", "order": "ASCENDING" },
        { "fieldPath": "createdAt", "order": "DESCENDING" }
      ]
    },
    {
      "collectionGroup": "fornecedores",
      "queryScope": "COLLECTION",
      "fields": [
        { "fieldPath": "status", "order": "ASCENDING" },
        { "fieldPath": "userId", "order": "ASCENDING" },
        { "fieldPath": "empresa", "order": "ASCENDING" }
      ]
    },
    {
      "collectionGroup": "quotations",
      "queryScope": "COLLECTION",
      "fields": [
        { "fieldPath": "userId", "order": "ASCENDING" },
        { "fieldPath": "shoppingListDate", "order": "DESCENDING" },
        { "fieldPath": "createdAt", "order": "DESCENDING" }
      ]
    },
    {
      "collectionGroup": "incoming_messages",
      "queryScope": "COLLECTION",
      "fields": [
        { "fieldPath": "userId", "order": "ASCENDING" },
        { "fieldPath": "createdAt", "order": "ASCENDING" }
      ]
    },
    {
      "collectionGroup": "shopping_list_items",
      "queryScope": "COLLECTION",
      "fields": [
        { "fieldPath": "userId", "order": "ASCENDING" },
        { "fieldPath": "listDate", "order": "DESCENDING" }
      ]
    },
    {
      "collectionGroup": "quotations",
      "queryScope": "COLLECTION",
      "fields": [
        { "fieldPath": "userId", "order": "ASCENDING" },
        { "fieldPath": "createdAt", "order": "DESCENDING" }
      ]
    },
    {
      "collectionGroup": "quotations",
      "queryScope": "COLLECTION",
      "fields": [
        { "fieldPath": "status", "order": "ASCENDING" },
        { "fieldPath": "deadline", "order": "DESCENDING" }
      ]
    },
    {
      "collectionGroup": "notifications",
      "queryScope": "COLLECTION",
      "fields": [
        { "fieldPath": "userId", "order": "ASCENDING" },
        { "fieldPath": "isRead", "order": "ASCENDING" }
      ]
    },
    {
      "collectionGroup": "notifications",
      "queryScope": "COLLECTION",
      "fields": [
        { "fieldPath": "userId", "order": "ASCENDING" },
        { "fieldPath": "quotationId", "order": "ASCENDING" },
        { "fieldPath": "createdAt", "order": "DESCENDING" }
      ]
    },
    {
      "collectionGroup": "notifications",
      "queryScope": "COLLECTION",
      "fields": [
        { "fieldPath": "userId", "order": "ASCENDING" },
        { "fieldPath": "type", "order": "ASCENDING" },
        { "fieldPath": "createdAt", "order": "DESCENDING" }
      ]
    },
    {
      "collectionGroup": "notifications",
      "queryScope": "COLLECTION",
      "fields": [
        { "fieldPath": "userId", "order": "ASCENDING" },
        { "fieldPath": "isRead", "order": "ASCENDING" },
        { "fieldPath": "createdAt", "order": "DESCENDING" }
      ]
    },
    {
      "collectionGroup": "pending_brand_requests",
      "queryScope": "COLLECTION",
      "fields": [
        { "fieldPath": "userId", "order": "ASCENDING" },
        { "fieldPath": "status", "order": "ASCENDING" }
      ]
    }
  ],
  "fieldOverrides": []
}